nextline_schedule/__about__.py
nextline_schedule/__init__.py
nextline_schedule/default.toml
nextline_schedule/dummy.py
nextline_schedule/plugin.py
nextline_schedule/py.typed
nextline_schedule/scheduler.py
nextline_schedule/types.py
nextline_schedule/auto/__init__.py
nextline_schedule/auto/auto_mode.py
nextline_schedule/auto/callback.py
nextline_schedule/auto/types.py
nextline_schedule/auto/state_machine/__init__.py
nextline_schedule/auto/state_machine/config.py
nextline_schedule/auto/state_machine/machine.py
nextline_schedule/graphql/__init__.py
nextline_schedule/graphql/mutations/auto_mode/ChangeMode.gql
nextline_schedule/graphql/mutations/auto_mode/TurnOff.gql
nextline_schedule/graphql/mutations/auto_mode/TurnOn.gql
nextline_schedule/graphql/mutations/queue/Push.gql
nextline_schedule/graphql/mutations/queue/Remove.gql
nextline_schedule/graphql/mutations/queue/move/OneBackward.gql
nextline_schedule/graphql/mutations/queue/move/OneForward.gql
nextline_schedule/graphql/mutations/queue/move/ToFirst.gql
nextline_schedule/graphql/mutations/queue/move/ToLast.gql
nextline_schedule/graphql/mutations/scheduler/LoadScript.gql
nextline_schedule/graphql/mutations/scheduler/Update.gql
nextline_schedule/graphql/queries/Version.gql
nextline_schedule/graphql/queries/auto_mode/Mode.gql
nextline_schedule/graphql/queries/auto_mode/State.gql
nextline_schedule/graphql/queries/queue/Items.gql
nextline_schedule/graphql/queries/scheduler/Preview.gql
nextline_schedule/graphql/queries/scheduler/Scheduler.gql
nextline_schedule/graphql/subscriptions/ScheduleAutoModeMode.gql
nextline_schedule/graphql/subscriptions/ScheduleAutoModeState.gql
nextline_schedule/graphql/subscriptions/ScheduleQueueItems.gql
nextline_schedule/queue/__init__.py
nextline_schedule/queue/item.py
nextline_schedule/queue/queue.py
nextline_schedule/queue/queue_imp.py
nextline_schedule/queue/strategies.py
nextline_schedule/schema/__init__.py
nextline_schedule/schema/mutation.py
nextline_schedule/schema/query.py
nextline_schedule-0.5.2.dist-info/METADATA
nextline_schedule-0.5.2.dist-info/WHEEL
nextline_schedule-0.5.2.dist-info/entry_points.txt
nextline_schedule-0.5.2.dist-info/licenses/LICENSE.txt
nextline_schedule-0.5.2.dist-info/RECORD
