Metadata-Version: 2.4
Name: nextline-schedule
Version: 0.5.2
Summary: A plugin of nextline-graphql. An interface to the SO scheduler.
Project-URL: Documentation, https://github.com/simonsobs/nextline-schedule#readme
Project-URL: Issues, https://github.com/simonsobs/nextline-schedule/issues
Project-URL: Source, https://github.com/simonsobs/nextline-schedule
Author-email: Simons Observatory <so_software@simonsobservatory.org>
License-Expression: MIT
License-File: LICENSE.txt
Classifier: Development Status :: 4 - Beta
Classifier: Intended Audience :: Science/Research
Classifier: License :: OSI Approved :: MIT License
Classifier: Programming Language :: Python
Classifier: Programming Language :: Python :: 3.10
Classifier: Programming Language :: Python :: 3.11
Classifier: Programming Language :: Python :: 3.12
Classifier: Programming Language :: Python :: 3.13
Requires-Python: >=3.10
Requires-Dist: httpx>=0.26
Requires-Dist: hypothesis>=6.88
Requires-Dist: nextline-graphql>=0.7.9
Requires-Dist: nextline>=0.7.19
Requires-Dist: transitions>=0.9
Provides-Extra: tests
Requires-Dist: deepdiff>=7.0; extra == 'tests'
Requires-Dist: nextline-test-utils>=0.1; extra == 'tests'
Requires-Dist: pytest-asyncio>=0.18; extra == 'tests'
Requires-Dist: pytest-cov>=3.0; extra == 'tests'
Requires-Dist: pytest-httpx>=0.29; extra == 'tests'
Requires-Dist: pytest-timeout>=2.1; extra == 'tests'
Requires-Dist: pytest>=8.2.1; extra == 'tests'
